AstroLib/AstroLib.py
AstroLib/__init__.py
Astro_Lib-0.0.1.dist-info/METADATA
Astro_Lib-0.0.1.dist-info/WHEEL
Astro_Lib-0.0.1.dist-info/top_level.txt
Astro_Lib-0.0.1.dist-info/RECORD
